pypi/__init__.py
foyou_pypi-0.0.9.dist-info/LICENSE
foyou_pypi-0.0.9.dist-info/METADATA
foyou_pypi-0.0.9.dist-info/WHEEL
foyou_pypi-0.0.9.dist-info/entry_points.txt
foyou_pypi-0.0.9.dist-info/top_level.txt
foyou_pypi-0.0.9.dist-info/RECORD
