Metadata-Version: 2.1
Name: foyou-pypi
Version: 0.0.9
Summary: python pypi package example
Home-page: https://github.com/foyoux/pypi-example
Author: foyoux
Author-email: yimi.0822@qq.com
License: GPL-3.0
Project-URL: Source, https://github.com/foyoux/pypi-example
Project-URL: Homepage, https://github.com/foyoux/pypi-example
Project-URL: Bug Tracker, https://github.com/foyoux/pypi-example/issues
Keywords: pypi-example
Classifier: Programming Language :: Python
Classifier: Programming Language :: Python :: 3
Classifier: Programming Language :: Python :: 3.7
Classifier: Programming Language :: Python :: 3.8
Classifier: Programming Language :: Python :: 3.9
Classifier: Programming Language :: Python :: 3.10
Classifier: Programming Language :: Python :: 3.11
Requires-Python: >=3.7
License-File: LICENSE
